setup.py
link_validator/__init__.py
link_validator/link_validator.py
link_validator.egg-info/PKG-INFO
link_validator.egg-info/SOURCES.txt
link_validator.egg-info/dependency_links.txt
link_validator.egg-info/entry_points.txt
link_validator.egg-info/not-zip-safe
link_validator.egg-info/requires.txt
link_validator.egg-info/top_level.txt