Metadata-Version: 1.0
Name: link-validator
Version: 0.2.2
Summary: Recursive link validator
Home-page: http://github.com/at1as/link-validator
Author: Jason Willems
Author-email: hello@jasonwillems.com
License: MIT
Platform: UNKNOWN
